Workbook

Sheet SBI FY 2021 - 2025
A1: State Bank of India: Master Raw Data Sheet (FY 2021 – FY 2025)
A2: All monetary figures are in ₹ Crores unless otherwise specified.
A3: Particulars | B3: FY 2020-21 | C3: FY 2021-22 | D3: FY 2022-23 | E3: FY 2023-24 | F3: FY 2024-25
A4: Total Assets | B4: 4534430 | C4: 4987597 | D4: 5516979 | E4: 6179694 | F4: 6676053
A5: Net Profit (PAT) | B5: 20410 | C5: 31676 | D5: 50232 | E5: 61077 | F5: 70901
A6: Total Deposits | B6: 3681277 | C6: 4051534 | D6: 4423778 | E6: 4916077 | F6: 5382190
A7: Net Advances | B7: 2449498 | C7: 2733967 | D7: 3199269 | E7: 3703971 | F7: 4163312
A8: Total Borrowings | B8: 417298 | C8: 426043 | D8: 493135 | E8: 597561 | F8: 563573
A9: Shareholder Equity* | B9: 253875 | C9: 280088 | D9: 327608 | E9: 377246 | F9: 441162
A10: Net NPA (%) | B10: 0.015 | C10: 0.0102 | D10: 0.0067 | E10: 0.0057 | F10: 0.0047
A11: CAR (%) (Basel III) | B11: 0.1374 | C11: 0.1383 | D11: 0.1468 | E11: 0.1428 | F11: 0.1425
A12: CASA Ratio (%) | B12: 0.4613 | C12: 0.4528 | D12: 0.438 | E12: 0.4111 | F12: 0.3439
A13: PCR (%) | B13: 0.8775 | C13: 0.902 | D13: 0.9191 | E13: 0.7502 | F13: 0.765
A15: *Calculated as Capital + Reserves & Surplus.

Sheet Ratio Analysis
A1: Bank | B1: Year | C1: Debt-Equity Ratio | D1: ROA (%) | E1: Net NPA (%) | F1: Credit-Deposit Ratio (%) | G1: CAR (%) | H1: CASA Ratio (%) | I1: PCR (%)
A2: SBI | B2: FY 2020-21 | C2: ='SBI FY 2021 - 2025'!$B8/'SBI FY 2021 - 2025'!$B9 -> 1.6437144 | D2: =('SBI FY 2021 - 2025'!B$5/'SBI FY 2021 - 2025'!B$4)*100 -> 0.4501117 | E2: ='SBI FY 2021 - 2025'!B10 -> 0.015 | F2: =('SBI FY 2021 - 2025'!B$7/'SBI FY 2021 - 2025'!B$6)*100 -> 66.539356 | G2: ='SBI FY 2021 - 2025'!B$11 -> 0.1374 | H2: ='SBI FY 2021 - 2025'!B12 -> 0.4613 | I2: ='SBI FY 2021 - 2025'!B13 -> 0.8775
A3: SBI | B3: FY 2021-22 | C3: ='SBI FY 2021 - 2025'!$C8/'SBI FY 2021 - 2025'!$C9 -> 1.5211041 | D3: =('SBI FY 2021 - 2025'!C$5/'SBI FY 2021 - 2025'!C$4)*100 -> 0.63509542 | E3: ='SBI FY 2021 - 2025'!C10 -> 0.0102 | F3: =('SBI FY 2021 - 2025'!C$7/'SBI FY 2021 - 2025'!C$6)*100 -> 67.479799 | G3: ='SBI FY 2021 - 2025'!C$11 -> 0.1383 | H3: ='SBI FY 2021 - 2025'!C12 -> 0.4528 | I3: ='SBI FY 2021 - 2025'!C13 -> 0.902
A4: SBI | B4: FY 2022-23 | C4: ='SBI FY 2021 - 2025'!$D8/'SBI FY 2021 - 2025'!$D9 -> 1.5052593 | D4: =('SBI FY 2021 - 2025'!D$5/'SBI FY 2021 - 2025'!D$4)*100 -> 0.9104983 | E4: ='SBI FY 2021 - 2025'!D10 -> 0.0067 | F4: =('SBI FY 2021 - 2025'!D$7/'SBI FY 2021 - 2025'!D$6)*100 -> 72.319836 | G4: ='SBI FY 2021 - 2025'!D$11 -> 0.1468 | H4: ='SBI FY 2021 - 2025'!D12 -> 0.438 | I4: ='SBI FY 2021 - 2025'!D13 -> 0.9191
A5: SBI | B5: FY 2023-24 | C5: ='SBI FY 2021 - 2025'!$E8/'SBI FY 2021 - 2025'!$E9 -> 1.5840088 | D5: =('SBI FY 2021 - 2025'!E$5/'SBI FY 2021 - 2025'!E$4)*100 -> 0.98834991 | E5: ='SBI FY 2021 - 2025'!E10 -> 0.0057 | F5: =('SBI FY 2021 - 2025'!E$7/'SBI FY 2021 - 2025'!E$6)*100 -> 75.34404 | G5: ='SBI FY 2021 - 2025'!E$11 -> 0.1428 | H5: ='SBI FY 2021 - 2025'!E12 -> 0.4111 | I5: ='SBI FY 2021 - 2025'!E13 -> 0.7502
A6: SBI | B6: FY 2024-25 | C6: ='SBI FY 2021 - 2025'!$F8/'SBI FY 2021 - 2025'!$F9 -> 1.277474 | D6: =('SBI FY 2021 - 2025'!F$5/'SBI FY 2021 - 2025'!F$4)*100 -> 1.0620197 | E6: ='SBI FY 2021 - 2025'!F10 -> 0.0047 | F6: =('SBI FY 2021 - 2025'!F$7/'SBI FY 2021 - 2025'!F$6)*100 -> 77.353494 | G6: ='SBI FY 2021 - 2025'!F$11 -> 0.1425 | H6: ='SBI FY 2021 - 2025'!F12 -> 0.3439 | I6: ='SBI FY 2021 - 2025'!F13 -> 0.765
A7: HDFC | B7: FY 2020-21 | C7: ='HDFC FY 2021 - 2025'!$B8/'HDFC FY 2021 - 2025'!$B9 -> 0.66501893 | D7: =('HDFC FY 2021 - 2025'!B$5/'HDFC FY 2021 - 2025'!B$4)*100 -> 1.7812706 | E7: ='HDFC FY 2021 - 2025'!B10 -> 0.004 | F7: =('HDFC FY 2021 - 2025'!B$7/'HDFC FY 2021 - 2025'!B$6)*100 -> 84.852891 | G7: ='HDFC FY 2021 - 2025'!B$11 -> 0.188 | H7: ='HDFC FY 2021 - 2025'!B$12 -> 0.461 | I7: ='HDFC FY 2021 - 2025'!B$13 -> 0.7
A8: HDFC | B8: FY 2021-22 | C8: ='HDFC FY 2021 - 2025'!$C8/'HDFC FY 2021 - 2025'!$C9 -> 0.7850352 | D8: =('HDFC FY 2021 - 2025'!C$5/'HDFC FY 2021 - 2025'!C$4)*100 -> 1.7868346 | E8: ='HDFC FY 2021 - 2025'!C10 -> 0.0032 | F8: =('HDFC FY 2021 - 2025'!C$7/'HDFC FY 2021 - 2025'!C$6)*100 -> 87.788999 | G8: ='HDFC FY 2021 - 2025'!C$11 -> 0.189 | H8: ='HDFC FY 2021 - 2025'!C$12 -> 0.482 | I8: ='HDFC FY 2021 - 2025'!C$13 -> 0.73
A9: HDFC | B9: FY 2022-23 | C9: ='HDFC FY 2021 - 2025'!$D8/'HDFC FY 2021 - 2025'!$D9 -> 0.73792385 | D9: =('HDFC FY 2021 - 2025'!D$5/'HDFC FY 2021 - 2025'!D$4)*100 -> 1.7886152 | E9: ='HDFC FY 2021 - 2025'!D10 -> 0.0027 | F9: =('HDFC FY 2021 - 2025'!D$7/'HDFC FY 2021 - 2025'!D$6)*100 -> 84.984085 | G9: ='HDFC FY 2021 - 2025'!D$11 -> 0.193 | H9: ='HDFC FY 2021 - 2025'!D$12 -> 0.444 | I9: ='HDFC FY 2021 - 2025'!D$13 -> 0.76
A10: HDFC | B10: FY 2023-24 | C10: ='HDFC FY 2021 - 2025'!$E8/'HDFC FY 2021 - 2025'!$E9 -> 1.5217623 | D10: =('HDFC FY 2021 - 2025'!E$5/'HDFC FY 2021 - 2025'!E$4)*100 -> 1.6810016 | E10: ='HDFC FY 2021 - 2025'!E10 -> 0.0033 | F10: =('HDFC FY 2021 - 2025'!E$7/'HDFC FY 2021 - 2025'!E$6)*100 -> 104.41535 | G10: ='HDFC FY 2021 - 2025'!E$11 -> 0.188 | H10: ='HDFC FY 2021 - 2025'!E$12 -> 0.382 | I10: ='HDFC FY 2021 - 2025'!E$13 -> 0.74
A11: HDFC | B11: FY 2024-25 | C11: ='HDFC FY 2021 - 2025'!$F8/'HDFC FY 2021 - 2025'!$F9 -> 1.3228936 | D11: =('HDFC FY 2021 - 2025'!F$5/'HDFC FY 2021 - 2025'!F$4)*100 -> 1.7223522 | E11: ='HDFC FY 2021 - 2025'!F10 -> 0.004 | F11: =('HDFC FY 2021 - 2025'!F$7/'HDFC FY 2021 - 2025'!F$6)*100 -> 96.496649 | G11: ='HDFC FY 2021 - 2025'!F$11 -> 0.196 | H11: ='HDFC FY 2021 - 2025'!F$12 -> 0.353 | I11: ='HDFC FY 2021 - 2025'!F$13 -> 0.6786
A12: ICICI | B12: FY 2020-21 | C12: ='ICICI FY 2021 - 2025'!$B8/'ICICI FY 2021 - 2025'!$B9 -> 0.62119343 | D12: =('ICICI FY 2021 - 2025'!B$5/'ICICI FY 2021 - 2025'!B$4)*100 -> 1.3160408 | E12: ='ICICI FY 2021 - 2025'!B10 -> 0.0114 | F12: =('ICICI FY 2021 - 2025'!B$7/'ICICI FY 2021 - 2025'!B$6)*100 -> 78.682219 | G12: ='ICICI FY 2021 - 2025'!B$11 -> 0.1912 | H12: ='ICICI FY 2021 - 2025'!B$12 -> 0.463 | I12: ='ICICI FY 2021 - 2025'!B$13 -> 0.777
A13: ICICI | B13: FY 2021-22 | C13: ='ICICI FY 2021 - 2025'!$C8/'ICICI FY 2021 - 2025'!$C9 -> 0.62836432 | D13: =('ICICI FY 2021 - 2025'!C$5/'ICICI FY 2021 - 2025'!C$4)*100 -> 1.6537259 | E13: ='ICICI FY 2021 - 2025'!C10 -> 0.0076 | F13: =('ICICI FY 2021 - 2025'!C$7/'ICICI FY 2021 - 2025'!C$6)*100 -> 80.691583 | G13: ='ICICI FY 2021 - 2025'!C$11 -> 0.1916 | H13: ='ICICI FY 2021 - 2025'!C$12 -> 0.487 | I13: ='ICICI FY 2021 - 2025'!C$13 -> 0.792
A14: ICICI | B14: FY 2022-23 | C14: ='ICICI FY 2021 - 2025'!$D8/'ICICI FY 2021 - 2025'!$D9 -> 0.59449966 | D14: =('ICICI FY 2021 - 2025'!D$5/'ICICI FY 2021 - 2025'!D$4)*100 -> 2.0133733 | E14: ='ICICI FY 2021 - 2025'!D10 -> 0.0048 | F14: =('ICICI FY 2021 - 2025'!D$7/'ICICI FY 2021 - 2025'!D$6)*100 -> 86.348458 | G14: ='ICICI FY 2021 - 2025'!D$11 -> 0.1834 | H14: ='ICICI FY 2021 - 2025'!D$12 -> 0.458 | I14: ='ICICI FY 2021 - 2025'!D$13 -> 0.828
A15: ICICI | B15: FY 2023-24 | C15: ='ICICI FY 2021 - 2025'!$E8/'ICICI FY 2021 - 2025'!$E9 -> 0.55353273 | D15: =('ICICI FY 2021 - 2025'!E$5/'ICICI FY 2021 - 2025'!E$4)*100 -> 2.1848977 | E15: ='ICICI FY 2021 - 2025'!E10 -> 0.0042 | F15: =('ICICI FY 2021 - 2025'!E$7/'ICICI FY 2021 - 2025'!E$6)*100 -> 83.832463 | G15: ='ICICI FY 2021 - 2025'!E$11 -> 0.1633 | H15: ='ICICI FY 2021 - 2025'!E$12 -> 0.422 | I15: ='ICICI FY 2021 - 2025'!E$13 -> 0.803
A16: ICICI | B16: FY 2024-25 | C16: ='ICICI FY 2021 - 2025'!$F8/'ICICI FY 2021 - 2025'!$F9 -> 0.5329691 | D16: =('ICICI FY 2021 - 2025'!F$5/'ICICI FY 2021 - 2025'!F$4)*100 -> 2.2295396 | E16: ='ICICI FY 2021 - 2025'!F10 -> 0.004 | F16: =('ICICI FY 2021 - 2025'!F$7/'ICICI FY 2021 - 2025'!F$6)*100 -> 83.321493 | G16: ='ICICI FY 2021 - 2025'!F$11 -> 0.166 | H16: ='ICICI FY 2021 - 2025'!F$12 -> 0.418 | I16: ='ICICI FY 2021 - 2025'!F$13 -> 0.81
A17: AXIS | B17: FY 2020-21 | C17: ='AXIS FY 2021 - 2025'!$B8/'AXIS FY 2021 - 2025'!$B9 -> 1.4061888 | D17: =('AXIS FY 2021 - 2025'!B$5/'AXIS FY 2021 - 2025'!B$4)*100 -> 0.66136743 | E17: ='AXIS FY 2021 - 2025'!B10 -> 0.0105 | F17: =('AXIS FY 2021 - 2025'!B$7/'AXIS FY 2021 - 2025'!B$6)*100 -> 88.182484 | G17: ='AXIS FY 2021 - 2025'!B$11 -> 0.1912 | H17: ='AXIS FY 2021 - 2025'!B$12 -> 0.45 | I17: ='AXIS FY 2021 - 2025'!B$13 -> 0.72
A18: AXIS | B18: FY 2021-22 | C18: ='AXIS FY 2021 - 2025'!$C8/'AXIS FY 2021 - 2025'!$C9 -> 1.6076242 | D18: =('AXIS FY 2021 - 2025'!C$5/'AXIS FY 2021 - 2025'!C$4)*100 -> 1.1083427 | E18: ='AXIS FY 2021 - 2025'!C10 -> 0.0073 | F18: =('AXIS FY 2021 - 2025'!C$7/'AXIS FY 2021 - 2025'!C$6)*100 -> 86.123636 | G18: ='AXIS FY 2021 - 2025'!C$11 -> 0.1854 | H18: ='AXIS FY 2021 - 2025'!C$12 -> 0.45 | I18: ='AXIS FY 2021 - 2025'!C$13 -> 0.75
A19: AXIS | B19: FY 2022-23 | C19: ='AXIS FY 2021 - 2025'!$D8/'AXIS FY 2021 - 2025'!$D9 -> 1.4854446 | D19: =('AXIS FY 2021 - 2025'!D$5/'AXIS FY 2021 - 2025'!D$4)*100 -> 0.72723077 | E19: ='AXIS FY 2021 - 2025'!D10 -> 0.0039 | F19: =('AXIS FY 2021 - 2025'!D$7/'AXIS FY 2021 - 2025'!D$6)*100 -> 89.266325 | G19: ='AXIS FY 2021 - 2025'!D$11 -> 0.1764 | H19: ='AXIS FY 2021 - 2025'!D$12 -> 0.47 | I19: ='AXIS FY 2021 - 2025'!D$13 -> 0.81
A20: AXIS | B20: FY 2023-24 | C20: ='AXIS FY 2021 - 2025'!$E8/'AXIS FY 2021 - 2025'!$E9 -> 1.2797619 | D20: =('AXIS FY 2021 - 2025'!E$5/'AXIS FY 2021 - 2025'!E$4)*100 -> 1.6829711 | E20: ='AXIS FY 2021 - 2025'!E10 -> 0.0031 | F20: =('AXIS FY 2021 - 2025'!E$7/'AXIS FY 2021 - 2025'!E$6)*100 -> 90.311097 | G20: ='AXIS FY 2021 - 2025'!E$11 -> 0.1663 | H20: ='AXIS FY 2021 - 2025'!E$12 -> 0.43 | I20: ='AXIS FY 2021 - 2025'!E$13 -> 0.79
A21: AXIS | B21: FY 2024-25 | C21: ='AXIS FY 2021 - 2025'!$F8/'AXIS FY 2021 - 2025'!$F9 -> 1.180274 | D21: =('AXIS FY 2021 - 2025'!F$5/'AXIS FY 2021 - 2025'!F$4)*100 -> 1.7190103 | E21: ='AXIS FY 2021 - 2025'!F10 -> 0.003 | F21: =('AXIS FY 2021 - 2025'!F$7/'AXIS FY 2021 - 2025'!F$6)*100 -> 89.825379 | G21: ='AXIS FY 2021 - 2025'!F$11 -> 0.1655 | H21: ='AXIS FY 2021 - 2025'!F$12 -> 0.405 | I21: ='AXIS FY 2021 - 2025'!F$13 -> 0.785
A22: PNB | B22: FY 2020-21 | C22: ='PNB FY 2021 - 2025'!$B8/'PNB FY 2021 - 2025'!$B9 -> 0.48980624 | D22: =('PNB FY 2021 - 2025'!B$5/'PNB FY 2021 - 2025'!B$4)*100 -> 0.16039561 | E22: ='PNB FY 2021 - 2025'!B10 -> 0.0573 | F22: =('PNB FY 2021 - 2025'!B$7/'PNB FY 2021 - 2025'!B$6)*100 -> 66.834097 | G22: ='PNB FY 2021 - 2025'!B$11 -> 0.1432 | H22: ='PNB FY 2021 - 2025'!B$12 -> 0.455 | I22: ='PNB FY 2021 - 2025'!B$13 -> 0.8014
A23: PNB | B23: FY 2021-22 | C23: ='PNB FY 2021 - 2025'!$C8/'PNB FY 2021 - 2025'!$C9 -> 0.45503576 | D23: =('PNB FY 2021 - 2025'!C$5/'PNB FY 2021 - 2025'!C$4)*100 -> 0.26292872 | E23: ='PNB FY 2021 - 2025'!C10 -> 0.048 | F23: =('PNB FY 2021 - 2025'!C$7/'PNB FY 2021 - 2025'!C$6)*100 -> 68.495113 | G23: ='PNB FY 2021 - 2025'!C$11 -> 0.145 | H23: ='PNB FY 2021 - 2025'!C$12 -> 0.474 | I23: ='PNB FY 2021 - 2025'!C$13 -> 0.816
A24: PNB | B24: FY 2022-23 | C24: ='PNB FY 2021 - 2025'!$D8/'PNB FY 2021 - 2025'!$D9 -> 0.5475139 | D24: =('PNB FY 2021 - 2025'!D$5/'PNB FY 2021 - 2025'!D$4)*100 -> 0.17149725 | E24: ='PNB FY 2021 - 2025'!D10 -> 0.0272 | F24: =('PNB FY 2021 - 2025'!D$7/'PNB FY 2021 - 2025'!D$6)*100 -> 69.052962 | G24: ='PNB FY 2021 - 2025'!D$11 -> 0.155 | H24: ='PNB FY 2021 - 2025'!D$12 -> 0.43 | I24: ='PNB FY 2021 - 2025'!D$13 -> 0.869
A25: PNB | B25: FY 2023-24 | C25: ='PNB FY 2021 - 2025'!$E8/'PNB FY 2021 - 2025'!$E9 -> 0.51842669 | D25: =('PNB FY 2021 - 2025'!E$5/'PNB FY 2021 - 2025'!E$4)*100 -> 0.52790468 | E25: ='PNB FY 2021 - 2025'!E10 -> 0.0073 | F25: =('PNB FY 2021 - 2025'!E$7/'PNB FY 2021 - 2025'!E$6)*100 -> 71.790587 | G25: ='PNB FY 2021 - 2025'!E$11 -> 0.1597 | H25: ='PNB FY 2021 - 2025'!E$12 -> 0.4144 | I25: ='PNB FY 2021 - 2025'!E$13 -> 0.9539
A26: PNB | B26: FY 2024-25 | C26: ='PNB FY 2021 - 2025'!$F8/'PNB FY 2021 - 2025'!$F9 -> 0.47187959 | D26: =('PNB FY 2021 - 2025'!F$5/'PNB FY 2021 - 2025'!F$4)*100 -> 0.91465544 | E26: ='PNB FY 2021 - 2025'!F10 -> 0.004 | F26: =('PNB FY 2021 - 2025'!F$7/'PNB FY 2021 - 2025'!F$6)*100 -> 71.276689 | G26: ='PNB FY 2021 - 2025'!F$11 -> 0.1701 | H26: ='PNB FY 2021 - 2025'!F$12 -> 0.3795 | I26: ='PNB FY 2021 - 2025'!F$13 -> 0.9682
A27: BOB | B27: FY 2020-21 | C27: ='BOB FY 2021 - 2025'!$B8/'BOB FY 2021 - 2025'!$B9 -> 1.2112102 | D27: =('BOB FY 2021 - 2025'!B$5/'BOB FY 2021 - 2025'!B$4)*100 -> 0.071747902 | E27: ='BOB FY 2021 - 2025'!B10 -> 0.0309 | F27: =('BOB FY 2021 - 2025'!B$7/'BOB FY 2021 - 2025'!B$6)*100 -> 73.040617 | G27: ='BOB FY 2021 - 2025'!B$11 -> 0.1499 | H27: ='BOB FY 2021 - 2025'!B$12 -> 0.4287 | I27: ='BOB FY 2021 - 2025'!B$13 -> 0.818
A28: BOB | B28: FY 2021-22 | C28: ='BOB FY 2021 - 2025'!$C8/'BOB FY 2021 - 2025'!$C9 -> 1.6653171 | D28: =('BOB FY 2021 - 2025'!C$5/'BOB FY 2021 - 2025'!C$4)*100 -> 0.59836688 | E28: ='BOB FY 2021 - 2025'!C10 -> 0.0172 | F28: =('BOB FY 2021 - 2025'!C$7/'BOB FY 2021 - 2025'!C$6)*100 -> 74.302182 | G28: ='BOB FY 2021 - 2025'!C$11 -> 0.1568 | H28: ='BOB FY 2021 - 2025'!C$12 -> 0.4424 | I28: ='BOB FY 2021 - 2025'!C$13 -> 0.8871
A29: BOB | B29: FY 2022-23 | C29: ='BOB FY 2021 - 2025'!$D8/'BOB FY 2021 - 2025'!$D9 -> 1.2204689 | D29: =('BOB FY 2021 - 2025'!D$5/'BOB FY 2021 - 2025'!D$4)*100 -> 1.0062695 | E29: ='BOB FY 2021 - 2025'!D10 -> 0.0089 | F29: =('BOB FY 2021 - 2025'!D$7/'BOB FY 2021 - 2025'!D$6)*100 -> 78.170866 | G29: ='BOB FY 2021 - 2025'!D$11 -> 0.1624 | H29: ='BOB FY 2021 - 2025'!D$12 -> 0.4225 | I29: ='BOB FY 2021 - 2025'!D$13 -> 0.9243
A30: BOB | B30: FY 2023-24 | C30: ='BOB FY 2021 - 2025'!$E8/'BOB FY 2021 - 2025'!$E9 -> 1.1235919 | D30: =('BOB FY 2021 - 2025'!E$5/'BOB FY 2021 - 2025'!E$4)*100 -> 1.1600693 | E30: ='BOB FY 2021 - 2025'!E10 -> 0.0068 | F30: =('BOB FY 2021 - 2025'!E$7/'BOB FY 2021 - 2025'!E$6)*100 -> 78.600859 | G30: ='BOB FY 2021 - 2025'!E$11 -> 0.1631 | H30: ='BOB FY 2021 - 2025'!E$12 -> 0.4115 | I30: ='BOB FY 2021 - 2025'!E$13 -> 0.933
A31: BOB | B31: FY 2024-25 | C31: ='BOB FY 2021 - 2025'!$F8/'BOB FY 2021 - 2025'!$F9 -> 0.97265312 | D31: =('BOB FY 2021 - 2025'!F$5/'BOB FY 2021 - 2025'!F$4)*100 -> 1.2298867 | E31: ='BOB FY 2021 - 2025'!F10 -> 0.0045 | F31: =('BOB FY 2021 - 2025'!F$7/'BOB FY 2021 - 2025'!F$6)*100 -> 78.968916 | G31: ='BOB FY 2021 - 2025'!F$11 -> 0.1719 | H31: ='BOB FY 2021 - 2025'!F$12 -> 0.3782 | I31: ='BOB FY 2021 - 2025'!F$13 -> 0.9475

Sheet HDFC FY 2021 - 2025
A1: HDFC Bank: Master Raw Data Sheet (FY 2021 – FY 2025)
A2: All monetary figures are in ₹ Crores unless otherwise specified.
A3: Particulars | B3: FY 2020-21 | C3: FY 2021-22 | D3: FY 2022-23 | E3: FY 2023-24* | F3: FY 2024-25*
A4: Total Assets | B4: 1746871 | C4: 2068535 | D4: 2466081 | E4: 3617623 | F4: 3910199
A5: Net Profit (PAT) | B5: 31116.5 | C5: 36961.3 | D5: 44108.7 | E5: 60812.3 | F5: 67347.4
A6: Total Deposits | B6: 1335060 | C6: 1559217 | D6: 1883395 | E6: 2379786 | F6: 2714715
A7: Total Advances | B7: 1132837 | C7: 1368821 | D7: 1600586 | E7: 2484862 | F7: 2619609
A8: Total Borrowings | B8: 135487.3 | C8: 188481.3 | D8: 206765.6 | E8: 666006.1 | F8: 663331.4
A9: Shareholder Equity | B9: 203734.5 | C9: 240092.8 | D9: 280199.1 | E9: 437654.5 | F9: 501424.6
A10: Net NPA (%) | B10: 0.004 | C10: 0.0032 | D10: 0.0027 | E10: 0.0033 | F10: 0.004
A11: CAR (%) | B11: 0.188 | C11: 0.189 | D11: 0.193 | E11: 0.188 | F11: 0.196
A12: CASA Ratio (%) | B12: 0.461 | C12: 0.482 | D12: 0.444 | E12: 0.382 | F12: 0.353
A13: PCR (%) | B13: 0.7 | C13: 0.73 | D13: 0.76 | E13: 0.74 | F13: 0.6786
A15: *Figures for FY24 and FY25 reflect the post-merger entity .

Sheet ICICI FY 2021 - 2025
A1: ICICI Bank: Master Raw Data Sheet (FY 2021 – FY 2025)
A2: All monetary figures are in ₹ Crores unless otherwise specified.
A3: Particulars | B3: FY 2020-21 | C3: FY 2021-22 | D3: FY 2022-23 | E3: FY 2023-24 | F3: FY 2024-25
A4: Total Assets | B4: 1230433 | C4: 1411298 | D4: 1584207 | E4: 1871392 | F4: 2118240
A5: Net Profit (PAT) | B5: 16193 | C5: 23339 | D5: 31896 | E5: 40888 | F5: 47227
A6: Total Deposits | B6: 932522 | C6: 1064572 | D6: 1180841 | E6: 1412825 | F6: 1610348
A7: Net Advances | B7: 733729 | C7: 859020 | D7: 1019638 | E7: 1184406 | F7: 1341766
A8: Total Borrowings | B8: 91631 | C8: 107231 | D8: 119325 | E8: 127700 | F8: 141450
A9: Shareholder Equity* | B9: 147508 | C9: 170651 | D9: 200715 | E9: 230700 | F9: 265400
A10: Net NPA (%) | B10: 0.0114 | C10: 0.0076 | D10: 0.0048 | E10: 0.0042 | F10: 0.004
A11: CAR (%) | B11: 0.1912 | C11: 0.1916 | D11: 0.1834 | E11: 0.1633 | F11: 0.166
A12: CASA Ratio (%) | B12: 0.463 | C12: 0.487 | D12: 0.458 | E12: 0.422 | F12: 0.418
A13: PCR (%) | B13: 0.777 | C13: 0.792 | D13: 0.828 | E13: 0.803 | F13: 0.81
A15: *Calculated as Capital + Reserves & Surplus.

Sheet AXIS FY 2021 - 2025
A1: Axis Bank: Master Raw Data Sheet (FY 2021 – FY 2025)
A2: All monetary figures are in ₹ Crores unless otherwise specified.
A3: Particulars | B3: FY 2020-21 | C3: FY 2021-22 | D3: FY 2022-23* | E3: FY 2023-24 | F3: FY 2024-25
A4: Total Assets | B4: 996118 | C4: 1175178 | D4: 1317326 | E4: 1477209 | F4: 1752171
A5: Net Profit (PAT) | B5: 6588 | C5: 13025 | D5: 9580 | E5: 24861 | F5: 30120
A6: Total Deposits | B6: 707306 | C6: 821721 | D6: 946945 | E6: 1068604 | F6: 1252430
A7: Net Advances | B7: 623720 | C7: 707696 | D7: 845303 | E7: 965068 | F7: 1125000
A8: Total Borrowings | B8: 142873 | C8: 185134 | D8: 186300 | E8: 193500 | F8: 215400
A9: Shareholder Equity | B9: 101603 | C9: 115160 | D9: 125417 | E9: 151200 | F9: 182500
A10: Net NPA (%) | B10: 0.0105 | C10: 0.0073 | D10: 0.0039 | E10: 0.0031 | F10: 0.003
A11: CAR (%) | B11: 0.1912 | C11: 0.1854 | D11: 0.1764 | E11: 0.1663 | F11: 0.1655
A12: CASA Ratio (%) | B12: 0.45 | C12: 0.45 | D12: 0.47 | E12: 0.43 | F12: 0.405
A13: PCR (%) | B13: 0.72 | C13: 0.75 | D13: 0.81 | E13: 0.79 | F13: 0.785
A15: *FY 2022-23 Net Profit was impacted by the one-time acquisition cost of Citibank's India Consumer Business.

Sheet PNB FY 2021 - 2025
A1: Punjab National Bank: Master Raw Data Sheet (FY 2021 – FY 2025)
A2: All monetary figures are in ₹ Crores unless otherwise specified.
A3: Particulars | B3: FY 2020-21 | C3: FY 2021-22 | D3: FY 2022-23 | E3: FY 2023-24 | F3: FY 2024-25
A4: Total Assets | B4: 1260633 | C4: 1314805 | D4: 1461831 | E4: 1561835 | F4: 1818171
A5: Net Profit (PAT) | B5: 2022 | C5: 3457 | D5: 2507 | E5: 8245 | F5: 16630
A6: Total Deposits | B6: 1106332 | C6: 1146219 | D6: 1281163 | E6: 1369713 | F6: 1566623
A7: Total Advances* | B7: 739407 | C7: 785104 | D7: 884681 | E7: 983325 | F7: 1116637
A8: Total Borrowings | B8: 44542 | C8: 43450 | D8: 54672 | E8: 55200 | F8: 60100
A9: Shareholder Equity | B9: 90938 | C9: 95487 | D9: 99855 | E9: 106476 | F9: 127363
A10: Net NPA (%) | B10: 0.0573 | C10: 0.048 | D10: 0.0272 | E10: 0.0073 | F10: 0.004
A11: CAR (%) | B11: 0.1432 | C11: 0.145 | D11: 0.155 | E11: 0.1597 | F11: 0.1701
A12: CASA Ratio (%) | B12: 0.455 | C12: 0.474 | D12: 0.43 | E12: 0.4144 | F12: 0.3795
A13: PCR (%)** | B13: 0.8014 | C13: 0.816 | D13: 0.869 | E13: 0.9539 | F13: 0.9682
A15: *Figures represent Gross Global Advances . **PCR including Technical Write-Offs (TWO).

Sheet BOB FY 2021 - 2025
A1: Bank of Baroda: Master Raw Data Sheet (FY 2021 – FY 2025)
A2: All monetary figures are in ₹ Crores unless otherwise specified.
A3: Particulars | B3: FY 2020-21 | C3: FY 2021-22 | D3: FY 2022-23 | E3: FY 2023-24 | F3: FY 2024-25
A4: Total Assets | B4: 1155364.8 | C4: 1215354.7 | D4: 1402171.1 | E4: 1533398.9 | F4: 1684335.7
A5: Net Profit (PAT) | B5: 828.95 | C5: 7272.28 | D5: 14109.62 | E5: 17788.49 | F5: 20715.42
A6: Total Deposits | B6: 966996.9 | C6: 1045938.6 | D6: 1203687.7 | E6: 1326957.5 | F6: 1472034.9
A7: Net Advances | B7: 706300.5 | C7: 777155.2 | D7: 940933.1 | E7: 1043000 | F7: 1162450
A8: Total Borrowings | B8: 66847.9 | C8: 103899.3 | D8: 92044.1 | E8: 105450 | F8: 112300
A9: Shareholder Equity* | B9: 55191 | C9: 62390.1 | D9: 75417 | E9: 93850.8 | F9: 115457.4
A10: Net NPA (%) | B10: 0.0309 | C10: 0.0172 | D10: 0.0089 | E10: 0.0068 | F10: 0.0045
A11: CAR (%) | B11: 0.1499 | C11: 0.1568 | D11: 0.1624 | E11: 0.1631 | F11: 0.1719
A12: CASA Ratio (%) | B12: 0.4287 | C12: 0.4424 | D12: 0.4225 | E12: 0.4115 | F12: 0.3782
A13: PCR (%)** | B13: 0.818 | C13: 0.8871 | D13: 0.9243 | E13: 0.933 | F13: 0.9475
A15: *Represents Net Worth (Paid-up Capital + Reserves & Surplus). **PCR including Technical Write-Offs (TWO).
